imagee/__init__.py
imagee-1.1.dist-info/METADATA
imagee-1.1.dist-info/WHEEL
imagee-1.1.dist-info/top_level.txt
imagee-1.1.dist-info/RECORD
