Metadata-Version: 2.1
Name: imagee
Version: 1.1
Summary: Tool for image optimization
Home-page: https://github.com/dev-muhammad/imagee
Author: dev-muhammad
Author-email: iam.markjobs@gmail.com
License: MIT
Keywords: image
Platform: UNKNOWN
Classifier: Development Status :: 5 - Production/Stable
Classifier: License :: OSI Approved :: MIT License
Classifier: Programming Language :: Python :: 3.8
Classifier: Topic :: Scientific/Engineering :: Image Processing
Requires-Dist: markdown
Requires-Dist: Pillow
